my_spoken_language_detection/__init__.py
myspokenlanguagedetection-5.dist-info/METADATA
myspokenlanguagedetection-5.dist-info/WHEEL
myspokenlanguagedetection-5.dist-info/top_level.txt
myspokenlanguagedetection-5.dist-info/RECORD
