Metadata-Version: 2.1
Name: myspokenlanguagedetection
Version: 5
Summary: Spoken language identification with CNN and RNN - Improved Version: accuracy up
Home-page: https://github.com/Shahabks/myspokenlanguageid
Author: Shahab Sabahi
Author-email: sabahi.s@mysol-gc.jp
License: MIT
Keywords: speech signal processing,Natural Language Processing and Understanding
Platform: UNKNOWN
Classifier: Intended Audience :: Developers
Classifier: Intended Audience :: Science/Research
Classifier: Programming Language :: Python
Classifier: Programming Language :: Python :: 3.7
Requires-Dist: numpy (>=1.15.2)
Requires-Dist: SpeechRecognition (>=3.8.1)
Requires-Dist: langdetect (>=1.0.7)
Requires-Dist: pickleshare (>=0.7.5)
Requires-Dist: nagisa (>=0.2.0)
